RISC_SingleCycle/SingleCycle_RISC.v
// Instruction Fetch

module ProgramCounter(branch,zero,clk,PCplus4, BranchInstr, address);
    input branch,clk,zero;
    input [7:0] BranchInstr; // max 64 instructions
    input [7:0] PCplus4;
    output reg [7:0] address;


    initial begin
        address = 8'b0;
    end

    always @(posedge clk) begin
        if (branch & zero) begin
            address <= BranchInstr;
        end else begin
            address <= PCplus4;
        end
    end

endmodule

module PC4adder(address, PCplus4);
    input [7:0] address;
    output [7:0] PCplus4;

    assign PCplus4 = address + 8'b000100;

endmodule

module InstructionMemory (address, instruction);
    input [7:0] address;
    output reg [31:0] instruction;
    
    reg [31:0] RAM [0:8]; 

    initial begin
    $readmemh("instructions.hex", RAM);
    end

    always @(*) begin
        instruction = RAM[address[7:2]];  
        $display("Now performing instruction @ PC=%h: %h", address, instruction);
    end

endmodule

// Instruction Decode

module RegisterFile (clk,rs,rt,rd,wdat,wen,read1,read2);
    input clk;
    input [4:0] rs,rt,rd;
    input [31:0] wdat;
    input wen;

    output reg [31:0] read1,read2;

    reg [31:0] Registers [31:0];

    integer i;
    initial begin
        for (i = 0; i < 32; i = i + 1)
            Registers[i] = 32'b0;
    end

    always @ (posedge clk) begin
        if (wen && rd != 0) begin
            Registers[rd] <= wdat;          // Its always rd here not like in MIPS
            $display("WRITE: x%0d <= %h (wdat), wen=%b, from module at time %t", rd, wdat, wen, $time);

        end
    end

    always @(*) begin
        read1 = Registers[rs];
        read2 = Registers[rt];
    end

endmodule

// Execution

module ControlCenter(opcode,f7,f3,ALUsel, wen, WBSel, ALUSrc, branch, memwriteen);
    input [6:0] opcode;
    input [6:0] f7;
    input [2:0] f3;
    output reg [3:0] ALUsel;
    output reg wen,WBSel, ALUSrc, branch, memwriteen;


    // send for slt sel[3] = 1

    always @(*) begin
        branch = 0; //reset
        ALUSrc = 1;
        memwriteen = 0;
        WBSel = 0;
        wen = 0;

        //ALU stuff
        if (opcode[4:0] == 5'b10011) begin
            ALUsel = {f7[5], f3};
            ALUSrc = opcode[5];     //if 1 then b otherwise immediate
            wen = 1;
        end

        //Branch stuff
        else if (opcode == 7'b1100011) begin
            branch = 1;
            case(f3)
                3'b000: ALUsel = 4'b1000;
                3'b001: ALUsel = 4'b1110;
                3'b100: ALUsel = 4'b0010;
                3'b101: ALUsel = 4'b1001;
                3'b110: ALUsel = 4'b1010;
                3'b111: ALUsel = 4'b1111;
            endcase
        end

        //Store word
        else if (opcode == 7'b0100011) begin
            memwriteen = 1;
        end 

        // Load full word and half word
        else if (opcode == 7'b0000011) begin
            WBSel = 1;
            wen = 1;
            ALUSrc = 0;
            ALUsel = 4'b0000;
        end


    end

endmodule


module ImmediateGenerator(instr,immediate);
    input [31:0] instr;
    output reg [31:0] immediate;

    always @(*) begin
        case (instr[6:0])
            7'b0110111: immediate = {instr[31:12], 12'b0};
            7'b0010111: immediate = {instr[31:12], 12'b0};
            7'b1101111: immediate = {{11{instr[31]}}, instr[31], instr[19:12], instr[20], instr[30:21], 1'b0};
            7'b1100011: immediate = {19'b0, instr[31], instr[7], instr[30:25], instr[11:8], 1'b0};
            7'b1100111: immediate = {20'b0, instr[31:20]};
            7'b0000011: immediate = {20'b0, instr[31:20]};
            7'b0010011: immediate = {20'b0, instr[31:20]};
            7'b0100011: immediate = {20'b0, instr[31:25], instr[11:7]};
            7'b0010011: immediate = {27'b0, instr[24:20]};

            default: immediate = 32'b0;

        endcase
    end

endmodule

module ImmediatePC4adder(immediate,PCplus4,BranchAddr);
    input [31:0] immediate;
    input [7:0] PCplus4;
    output [7:0] BranchAddr;

    assign BranchAddr = PCplus4 + immediate[7:0];

endmodule


module ALU ( a, b, imm, ALUSrc, sel, out, zero);
    input [31:0] a;
    input [31:0] b;
    input [31:0] imm;
    input ALUSrc;
    input [3:0] sel;
    output reg [31:0] out;
    output reg zero;
    reg [31:0] bornotb, sum;
    reg [31:0] operand2;


    always @(*) begin
        operand2 = ALUSrc ? b : imm;

        bornotb = sel[3] ? ~operand2 : operand2;
        sum = a + bornotb + sel[3];         // Just for sub

    end

    always @ (a or b or imm or sel)
    begin

        case (sel[3:0])
            4'b0000: out = sum;
            4'b1000: begin
                out = sum;
                zero = (sum == 0);
            end
            4'b0001: out = a << (operand2[4:0]);
            4'b0010: begin
                out = ($signed(a) < $signed(operand2) ) ? 1 : 0; //not all bits like I thought
                zero = out[0];
            end
            4'b0011: out = (a<operand2) ? 1 : 0;
            4'b0100: out = a^operand2;
            4'b0101: out = a >> (operand2[4:0]);
            4'b1101: out = $signed(a) >>> (operand2[4:0]);
            4'b0110: out = a | operand2;
            4'b0111: out = a & operand2;

            // Just made new ones for branching
            4'b1110: zero = (a != operand2);
            4'b1001: zero = ($signed(a) > $signed(operand2));
            4'b1010: zero = ((a) <= (operand2));
            4'b1111: zero = ((a) > (operand2));




            default : out = 32'b0;

        endcase

        $display("ALU: a=%h, b(or immediate)=%h, sel=%b, result=%h", a, operand2, sel, out);

    end
endmodule

// Memory Access

module DataMemory(clk, address, wdat, memwriteen, readD);
    input clk;
    input [31:0] address;
    input [31:0] wdat;
    input memwriteen;
    output [31:0] readD;

    reg [31:0] DRAM [63:0];

    integer i;
    initial begin
        for (i = 0; i < 64; i = i + 1)
            DRAM[i] = 32'b0;
    end

    assign readD = DRAM[address[7:2]];

    always @(posedge clk) begin
        if (memwriteen) begin
            DRAM[address[7:2]] <= wdat;
            $display("Address: %h now has data: %h", address[31:2],wdat);
        end
    end
endmodule

// WriteBack

module WriteBackMUX(ALUResult, LoadData, WBSel, WriteBack);
    input [31:0] ALUResult, LoadData;
    input WBSel;

    output reg [31:0] WriteBack;

    always @(*) begin
        WriteBack = WBSel ? LoadData : ALUResult;
    end

endmodule



// RISC

module Processor (clk);
    input clk;

    wire branch;
    wire [7:0] BranchInstr,address;

    wire [7:0] PCplus4;

    wire [31:0] instruction;

    wire wen;
    wire [31:0] wdat,read1,read2;

    wire [3:0] ALUsel;
    wire ALUSrc;
    wire[31:0] immExtended;
    wire [31:0] ALUResult;

    wire memwriteen;

    wire [31:0] loadfromMem;

    wire WBSel;

    wire zero;


    ProgramCounter PC (
        .branch(branch),
        .BranchInstr(BranchInstr),
        .address(address),
        .zero(zero),
        .clk(clk),
        .PCplus4(PCplus4)
    );


    PC4adder pc4 (
        .address(address),
        .PCplus4(PCplus4)
    );



    InstructionMemory IM (
        .address(address),
        .instruction(instruction)
    );

    RegisterFile RF (
        .clk(clk),
        .rs(instruction[19:15]),
        .rt(instruction[24:20]),
        .rd(instruction[11:7]),
        .wdat(wdat),
        .wen(wen),
        .read1(read1),
        .read2(read2)
    );

    ControlCenter Ctrl (
        .opcode(instruction[6:0]),
        .f7(instruction[31:25]),
        .f3(instruction[14:12]),
        .ALUsel(ALUsel),
        .memwriteen(memwriteen),
        .wen(wen),
        .WBSel(WBSel), 
        .branch(branch), 
        .ALUSrc(ALUSrc)
    );

    ImmediateGenerator ImG (
        .instr(instruction),
        .immediate(immExtended)
    );

    ImmediatePC4adder IPC4(
        .immediate(immExtended),
        .PCplus4(PCplus4),
        .BranchAddr(BranchInstr)
    );


    ALU alu (
        .a(read1),
        .b(read2),
        .imm(immExtended),
        .ALUSrc(ALUSrc),
        .sel(ALUsel),
        .out(ALUResult),
        .zero(zero)

    );


    DataMemory DM (
        .clk(clk),
        .address(ALUResult),
        .wdat(read2),
        .memwriteen(memwriteen),
        .readD(loadfromMem)
    );

    WriteBackMUX WB (
        .ALUResult(ALUResult),
        .LoadData(loadfromMem),
        .WBSel(WBSel),
        .WriteBack(wdat)
    );



endmodule



module Testbench;

    // Clock signal
    reg clk;

    // Instantiate the processor
    Processor dut (
        .clk(clk)
    );

    // Clock generation: 10ns period
    initial begin
        clk = 0;
        forever #5 clk = ~clk;  // Toggle every 5ns → 10ns period
    end

    // Simulation control
    initial begin
        // Optional: dump variables
        $display("Simulation starting...");
        $dumpfile("dump.vcd");
        $dumpvars(0, dut);  // dumps all vars in Processor

        #100;  // Run for 1000ns (100 clock cycles)
        $display("Simulation done.");
        $finish;
    end

endmodule

RISC_SingleCycle/dump.vcd
$date
	Tue Jun 24 20:33:24 2025
$end
$version
	Icarus Verilog
$end
$timescale
	1s
$end
$scope module Testbench $end
$scope module dut $end
$var wire 1 ! clk $end
$var wire 1 " zero $end
$var wire 1 # wen $end
$var wire 32 $ wdat [31:0] $end
$var wire 32 % read2 [31:0] $end
$var wire 32 & read1 [31:0] $end
$var wire 1 ' memwriteen $end
$var wire 32 ( loadfromMem [31:0] $end
$var wire 32 ) instruction [31:0] $end
$var wire 32 * immExtended [31:0] $end
$var wire 1 + branch $end
$var wire 8 , address [7:0] $end
$var wire 1 - WBSel $end
$var wire 8 . PCplus4 [7:0] $end
$var wire 8 / BranchInstr [7:0] $end
$var wire 4 0 ALUsel [3:0] $end
$var wire 1 1 ALUSrc $end
$var wire 32 2 ALUResult [31:0] $end
$scope module Ctrl $end
$var wire 3 3 f3 [2:0] $end
$var wire 7 4 f7 [6:0] $end
$var wire 7 5 opcode [6:0] $end
$var reg 1 1 ALUSrc $end
$var reg 4 6 ALUsel [3:0] $end
$var reg 1 - WBSel $end
$var reg 1 + branch $end
$var reg 1 ' memwriteen $end
$var reg 1 # wen $end
$upscope $end
$scope module DM $end
$var wire 1 ! clk $end
$var wire 1 ' memwriteen $end
$var wire 32 7 readD [31:0] $end
$var wire 32 8 wdat [31:0] $end
$var wire 32 9 address [31:0] $end
$var integer 32 : i [31:0] $end
$upscope $end
$scope module IM $end
$var wire 8 ; address [7:0] $end
$var reg 32 < instruction [31:0] $end
$upscope $end
$scope module IPC4 $end
$var wire 32 = immediate [31:0] $end
$var wire 8 > PCplus4 [7:0] $end
$var wire 8 ? BranchAddr [7:0] $end
$upscope $end
$scope module ImG $end
$var wire 32 @ instr [31:0] $end
$var reg 32 A immediate [31:0] $end
$upscope $end
$scope module PC $end
$var wire 8 B BranchInstr [7:0] $end
$var wire 1 + branch $end
$var wire 1 ! clk $end
$var wire 1 " zero $end
$var wire 8 C PCplus4 [7:0] $end
$var reg 8 D address [7:0] $end
$upscope $end
$scope module RF $end
$var wire 1 ! clk $end
$var wire 5 E rd [4:0] $end
$var wire 5 F rs [4:0] $end
$var wire 5 G rt [4:0] $end
$var wire 1 # wen $end
$var wire 32 H wdat [31:0] $end
$var reg 32 I read1 [31:0] $end
$var reg 32 J read2 [31:0] $end
$var integer 32 K i [31:0] $end
$upscope $end
$scope module WB $end
$var wire 32 L LoadData [31:0] $end
$var wire 1 - WBSel $end
$var wire 32 M ALUResult [31:0] $end
$var reg 32 N WriteBack [31:0] $end
$upscope $end
$scope module alu $end
$var wire 1 1 ALUSrc $end
$var wire 32 O a [31:0] $end
$var wire 32 P b [31:0] $end
$var wire 32 Q imm [31:0] $end
$var wire 4 R sel [3:0] $end
$var reg 32 S bornotb [31:0] $end
$var reg 32 T operand2 [31:0] $end
$var reg 32 U out [31:0] $end
$var reg 32 V sum [31:0] $end
$var reg 1 " zero $end
$upscope $end
$scope module pc4 $end
$var wire 8 W address [7:0] $end
$var wire 8 X PCplus4 [7:0] $end
$upscope $end
$upscope $end
$upscope $end
$enddefinitions $end
$comment Show the parameter values. $end
$dumpall
$end
#0
$dumpvars
b100 X
b0 W
b101 V
b101 U
b101 T
b101 S
b0 R
b101 Q
b0 P
b0 O
b101 N
b101 M
b0 L
b100000 K
b0 J
b0 I
b101 H
b101 G
b0 F
b1 E
b0 D
b100 C
b1001 B
b101 A
b10100000000000010010011 @
b1001 ?
b100 >
b101 =
b10100000000000010010011 <
b0 ;
b1000000 :
b101 9
b0 8
b0 7
b0 6
b10011 5
b0 4
b0 3
b101 2
01
b0 0
b1001 /
b100 .
0-
b0 ,
0+
b101 *
b10100000000000010010011 )
b0 (
0'
b0 &
b0 %
b101 $
1#
x"
0!
$end
#5
b1010 $
b1010 H
b1010 N
b1010 2
b1010 9
b1010 M
b1010 U
b1010 V
b1010 S
b1010 T
b1010 *
b1010 =
b1010 A
b1010 Q
b10 E
b1010 G
b101000000000000100010011 )
b101000000000000100010011 <
b101000000000000100010011 @
b10010 /
b10010 ?
b10010 B
b1000 .
b1000 >
b1000 C
b1000 X
b100 ,
b100 ;
b100 D
b100 W
1!
#10
0!
#15
b1111 $
b1111 H
b1111 N
b1111 2
b1111 9
b1111 M
b1111 U
b1111 V
1#
11
b1010 %
b1010 8
b1010 J
b1010 P
b101 &
b101 I
b101 O
b0 *
b0 =
b0 A
b0 Q
b110011 5
b11 E
b10 G
b1 F
b1000001000000110110011 )
b1000001000000110110011 <
b1000001000000110110011 @
b1100 /
b1100 ?
b1100 B
b1100 .
b1100 >
b1100 C
b1100 X
b1000 ,
b1000 ;
b1000 D
b1000 W
1!
#20
0!
#25
b1111 S
b1111 T
1'
0#
b1111 %
b1111 8
b1111 J
b1111 P
b0 &
b0 I
b0 O
b10 3
b100011 5
b0 E
b11 G
b0 F
b1100000010000000100011 )
b1100000010000000100011 <
b1100000010000000100011 @
b10000 /
b10000 ?
b10000 B
b10000 .
b10000 >
b10000 C
b10000 X
b1100 ,
b1100 ;
b1100 D
b1100 W
1!
#30
0!
#35
b0 $
b0 H
b0 N
b0 2
b0 9
b0 M
b0 U
b0 V
b0 S
b0 T
01
1#
1-
0'
b0 %
b0 8
b0 J
b0 P
b11 5
b100 E
b0 G
b10001000000011 )
b10001000000011 <
b10001000000011 @
b0 (
b0 7
b0 L
b10100 /
b10100 ?
b10100 B
b10100 .
b10100 >
b10100 C
b10100 X
b10000 ,
b10000 ;
b10000 D
b10000 W
1!
#40
0!
#45
b11111111111111111111111111111011 $
b11111111111111111111111111111011 H
b11111111111111111111111111111011 N
0"
b11111111111111111111111111111011 2
b11111111111111111111111111111011 9
b11111111111111111111111111111011 M
b11111111111111111111111111111011 U
b11111111111111111111111111111011 V
b11111111111111111111111111111010 S
b101 T
b1000 0
b1000 6
b1000 R
1#
0-
11
b101 %
b101 8
b101 J
b101 P
b0 3
b100000 4
b110011 5
b101 E
b1 G
b100 F
b1000000000100100000001010110011 )
b1000000000100100000001010110011 <
b1000000000100100000001010110011 @
b11000 /
b11000 ?
b11000 B
b11000 .
b11000 >
b11000 C
b11000 X
b10100 ,
b10100 ;
b10100 D
b10100 W
1!
#50
0!
#55
b1 $
b1 H
b1 N
1"
b1 2
b1 9
b1 M
b1 U
b1111 V
b1010 S
b1010 T
b10 0
b10 6
b10 R
1#
b1010 %
b1010 8
b1010 J
b1010 P
b101 &
b101 I
b101 O
b10 3
b0 4
b110 E
b10 G
b1 F
b1000001010001100110011 )
b1000001010001100110011 <
b1000001010001100110011 @
b11100 /
b11100 ?
b11100 B
b11100 .
b11100 >
b11100 C
b11100 X
b11000 ,
b11000 ;
b11000 D
b11000 W
1!
#60
0!
#65
1+
0#
b1000 *
b1000 =
b1000 A
b1000 Q
b100 3
b1100011 5
b1000 E
b1000001100010001100011 )
b1000001100010001100011 <
b1000001100010001100011 @
b101000 /
b101000 ?
b101000 B
b100000 .
b100000 >
b100000 C
b100000 X
b11100 ,
b11100 ;
b11100 D
b11100 W
1!
#70
0!
#75
b0x $
b0x H
b0x N
x"
b0x 2
b0x 9
b0x M
b0x U
bx V
bx S
bx T
0+
bx %
bx 8
bx J
bx P
bx &
bx I
bx O
b0 *
b0 =
b0 A
b0 Q
bx 3
bx 4
bx 5
bx E
bx G
bx F
bx )
bx <
bx @
b101100 /
b101100 ?
b101100 B
b101100 .
b101100 >
b101100 C
b101100 X
b101000 ,
b101000 ;
b101000 D
b101000 W
1!
#80
0!
#85
b110000 /
b110000 ?
b110000 B
b110000 .
b110000 >
b110000 C
b110000 X
b101100 ,
b101100 ;
b101100 D
b101100 W
1!
#90
0!
#95
b110100 /
b110100 ?
b110100 B
b110100 .
b110100 >
b110100 C
b110100 X
b110000 ,
b110000 ;
b110000 D
b110000 W
1!
